Workbook

Sheet 📊 Dashboard Laba Rugi
A1: LAPORAN LABA RUGI PENJUALAN MARKETPLACE 2026
A2: Template Otomatis Pembukuan Toko Shopee, Tokopedia & TikTok Shop
A4: Komponen Finansial | B4: Nilai (Rp) | C4: Persentase (%) | D4: Keterangan
A5: Total Omzet Penjualan Kotor (Gross Sales) | B5: ='🛒 Rekap Penjualan'!G20 | C5: =B5/B5 | D5: Total nilai transaksi penjualan sebelum potongan
A6: Total Potongan Komisi Marketplace | B6: ='🛒 Rekap Penjualan'!H20 | C6: =B6/B5 | D6: Potongan admin, gratis ongkir & promo marketplace
A7: Total Uang Bersih Diterima (Net Revenue) | B7: =B5-B6 | C7: =B7/B5 | D7: Saldo bersih masuk ke rekening/saldo penjual
A8: Total HPP / Modal Produk | B8: ='🛒 Rekap Penjualan'!J20 | C8: =B8/B5 | D8: Total akumulasi modal beli/produksi barang
A9: Total Biaya Packing | B9: ='🛒 Rekap Penjualan'!K20 | C9: =B9/B5 | D9: Total plastik polymailer, kardus, bubble wrap
A10: Total Biaya Operasional & Iklan (Ads) | B10: ='💸 Pengeluaran'!C20 | C10: =B10/B5 | D10: Pengeluaran iklan marketplace, gaji, software
A11: TOTAL LABA BERSIH (NET PROFIT) | B11: =B7-B8-B9-B10 | C11: =B11/B5 | D11: Keuntungan bersih akhir yang didapatkan toko

Sheet 🛒 Rekap Penjualan
A1: Tanggal | B1: No. Pesanan | C1: Marketplace | D1: Nama Produk | E1: Qty | F1: Harga Jual (Rp) | G1: Total Omzet (Rp) | H1: Komisi Marketplace (Rp) | I1: Saldo Diterima (Rp) | J1: HPP Modal (Rp) | K1: Biaya Packing (Rp) | L1: Profit Bersih (Rp)
A2: 2026-07-01 | B2: 260701SHP001 | C2: Shopee | D2: Kemeja Oversize Linen | E2: 1 | F2: 150000 | G2: =E2*F2 | H2: 21000 | I2: =G2-H2 | J2: 85000 | K2: 3000 | L2: =I2-J2-K2
A3: 2026-07-01 | B3: 260701TKP002 | C3: Tokopedia | D3: Celana Chino Slimfit | E3: 2 | F3: 180000 | G3: =E3*F3 | H3: 32400 | I3: =G3-H3 | J3: 200000 | K3: 5000 | L3: =I3-J3-K3
A4: 2026-07-02 | B4: 260702TIK003 | C4: TikTok Shop | D4: Kaos Polos Cotton Combed | E4: 3 | F4: 65000 | G4: =E4*F4 | H4: 22425 | I4: =G4-H4 | J4: 105000 | K4: 4500 | L4: =I4-J4-K4
A5: 2026-07-02 | B5: 260702SHP004 | C5: Shopee | D5: Jaket Varsity Vintage | E5: 1 | F5: 280000 | G5: =E5*F5 | H5: 39200 | I5: =G5-H5 | J5: 160000 | K5: 4000 | L5: =I5-J5-K5
A20: TOTAL SUMMARY | E20: =SUM(E2:E19) | F20: =SUM(F2:F19) | G20: =SUM(G2:G19) | H20: =SUM(H2:H19) | I20: =SUM(I2:I19) | J20: =SUM(J2:J19) | K20: =SUM(K2:K19) | L20: =SUM(L2:L19)

Sheet 📦 Database Stok & HPP
A1: Kode SKU | B1: Nama Produk | C1: Kategori | D1: HPP Modal (Rp) | E1: Biaya Packing (Rp) | F1: Harga Jual Disarankan (Rp) | G1: Stok Awal | H1: Terjual | I1: Sisa Stok | J1: Nilai Aset Stok (Rp)
A2: SKU-FSH-001 | B2: Kemeja Oversize Linen | C2: Fashion | D2: 85000 | E2: 3000 | F2: 150000 | G2: 100 | H2: 15 | I2: =G2-H2 | J2: =I2*D2
A3: SKU-FSH-002 | B3: Celana Chino Slimfit | C3: Fashion | D3: 100000 | E3: 2500 | F3: 180000 | G3: 80 | H3: 22 | I3: =G3-H3 | J3: =I3*D3
A4: SKU-FSH-003 | B4: Kaos Polos Cotton Combed | C4: Fashion | D4: 35000 | E4: 1500 | F4: 65000 | G4: 200 | H4: 45 | I4: =G4-H4 | J4: =I4*D4
A5: SKU-FSH-004 | B5: Jaket Varsity Vintage | C5: Fashion | D5: 160000 | E5: 4000 | F5: 280000 | G5: 50 | H5: 8 | I5: =G5-H5 | J5: =I5*D5

Sheet 💸 Pengeluaran
A1: Tanggal | B1: Kategori Pengeluaran | C1: Nominal Pengeluaran (Rp) | D1: Keterangan / Catatan
A2: 2026-07-01 | B2: Iklan Shopee Ads | C2: 150000 | D2: Top-up saldo iklan Shopee
A3: 2026-07-02 | B3: Iklan TikTok Shop (GMV Max) | C3: 200000 | D3: Kempen promosi tanggal kembar
A4: 2026-07-03 | B4: Bahan Packing (Plastik Polymailer) | C4: 85000 | D4: Beli 100 pcs plastik ukuran L
A5: 2026-07-05 | B5: Gaji Admin Packing | C5: 500000 | D5: Uang harian tim packing pesanan
A20: TOTAL PENGELUARAN | C20: =SUM(C2:C19)
